MANIFEST.in
README.md
setup.cfg
setup.py
bin/hypergan
hypergan/__init__.py
hypergan/cli.py
hypergan/configurable_component.py
hypergan/configuration.py
hypergan/gan.py
hypergan/gan_component.py
hypergan/layer.py
hypergan/layer_shape.py
hypergan/parser.py
hypergan/threaded_tk_viewer.py
hypergan/viewer.py
hypergan.egg-info/PKG-INFO
hypergan.egg-info/SOURCES.txt
hypergan.egg-info/dependency_links.txt
hypergan.egg-info/top_level.txt
hypergan/accelerators/gpu_backend.py
hypergan/configurations/__init__.py
hypergan/configurations/aligned_interpolated.json
hypergan/configurations/classification.json
hypergan/configurations/colorizer.json
hypergan/configurations/configurable.json
hypergan/configurations/dcgan.json
hypergan/configurations/default.json
hypergan/configurations/generate_readme.py
hypergan/configurations/generate_samples.py
hypergan/configurations/model_scaling.json
hypergan/configurations/replace_hyperparms.py
hypergan/configurations/run_all.py
hypergan/configurations/stylegan.json
hypergan/configurations/components/losses/ali_loss/ali_loss_1.json
hypergan/configurations/components/losses/f_divergence_loss/f_divergence_loss_1.json
hypergan/configurations/components/losses/f_divergence_loss/f_divergence_loss_2.json
hypergan/configurations/components/losses/f_divergence_loss/f_divergence_loss_3.json
hypergan/configurations/components/losses/least_squares_loss/least_squares_loss_1.json
hypergan/configurations/components/losses/logistic_loss/logistic_loss_1.json
hypergan/configurations/components/losses/qp_loss/qp_loss_1.json
hypergan/configurations/components/losses/ragan_loss/ragan_loss_1.json
hypergan/configurations/components/losses/ragan_loss/ragan_loss_2.json
hypergan/configurations/components/losses/realness_loss/realness_loss_1.json
hypergan/configurations/components/losses/softmax_loss/softmax_loss_1.json
hypergan/configurations/components/losses/standard_loss/standard_loss_1.json
hypergan/configurations/components/losses/wasserstein_loss/wasserstein_loss_1.json
hypergan/configurations/components/losses/wasserstein_loss/wasserstein_loss_2.json
